libazuretls.so
httpz/__init__.py
httpz/client.py
httpz/utils.py
httpz_ja3-0.1.0.dist-info/METADATA
httpz_ja3-0.1.0.dist-info/WHEEL
httpz_ja3-0.1.0.dist-info/top_level.txt
httpz_ja3-0.1.0.dist-info/RECORD
