Metadata-Version: 2.4
Name: httpz-ja3
Version: 0.1.0
Summary: A HTTP client library with JA3 spoofing capabilities
Author-email: httpz Contributors <info@httpz.io>
Project-URL: Homepage, https://github.com/username/httpz
Project-URL: Bug Tracker, https://github.com/username/httpz/issues
Classifier: Programming Language :: Python :: 3
Classifier: Programming Language :: Python :: 3.8
Classifier: Programming Language :: Python :: 3.9
Classifier: Programming Language :: Python :: 3.10
Classifier: Programming Language :: Python :: 3.11
Classifier: License :: OSI Approved :: MIT License
Classifier: Operating System :: OS Independent
Classifier: Topic :: Internet :: WWW/HTTP
Classifier: Topic :: Software Development :: Libraries :: Python Modules
Requires-Python: >=3.8
Requires-Dist: requests>=2.25.0
Requires-Dist: cffi>=1.14.0
